{
  "facebook": "",
  "stackoverflow": "",
  "twitter": "https://twitter.com/midwestdevwork",
  "instagram": "https://instagram.com/",
  "youtube": "https://www.youtube.com/@midwestdevelopment",
  "linkedin": "https://linkedin.com/anacecyflores",
  "github": "https://github.com/anacecyflores1",
  "gitlab": "",
  "discord": "",
  "slack": "",
  "medium": "",
  "codepen": "",
  "bitbucket": "",
  "dribbble": "",
  "behance": "",
  "pinterest": "",
  "soundcloud": "",
  "tumblr": "",
  "reddit": "",
  "vk": "",
  "whatsapp": "",
  "snapchat": "",
  "vimeo": "",
  "tiktok": "",
  "foursquare": "",
  "rss": "",
  "email": "anacecyflores1@gmail.com",
  "phone": "+17737049030",
  "address": "",
  "skype": "",
  "website": "https://www.midwestdev.net/"
}
